{"version":"4.5.0","objects":[{"type":"textbox","version":"4.5.0","originX":"left","originY":"top","left":110.78,"top":134.97,"width":82.19,"height":75.03,"fill":"black","stroke":null,"strokeWidth":1,"strokeDashArray":null,"strokeLineCap":"butt","strokeDashOffset":0,"strokeLineJoin":"miter","strokeUniform":false,"strokeMiterLimit":4,"scaleX":1,"scaleY":1,"angle":0,"flipX":false,"flipY":false,"opacity":1,"shadow":null,"visible":true,"backgroundColor":"","fillRule":"nonzero","paintFirst":"fill","globalCompositeOperation":"source-over","skewX":0,"skewY":0,"text":"this is a temporary text","fontSize":20,"fontWeight":"normal","fontFamily":"Times New Roman","fontStyle":"normal","lineHeight":1.16,"underline":false,"overline":false,"linethrough":false,"textAlign":"left","textBackgroundColor":"","charSpacing":0,"path":null,"direction":"ltr","minWidth":20,"splitByGrapheme":false,"styles":{}},{"type":"textbox","version":"4.5.0","originX":"left","originY":"top","left":125.75,"top":462.9,"width":155.69,"height":141.57,"fill":"#e60000","stroke":null,"strokeWidth":1,"strokeDashArray":null,"strokeLineCap":"butt","strokeDashOffset":0,"strokeLineJoin":"miter","strokeUniform":false,"strokeMiterLimit":4,"scaleX":1.17,"scaleY":1.17,"angle":0,"flipX":false,"flipY":false,"opacity":1,"shadow":null,"visible":true,"backgroundColor":"","fillRule":"nonzero","paintFirst":"fill","globalCompositeOperation":"source-over","skewX":0,"skewY":0,"text":"big test","fontSize":58,"fontWeight":"normal","fontFamily":"Times New Roman","fontStyle":"normal","lineHeight":1.16,"underline":false,"overline":false,"linethrough":false,"textAlign":"left","textBackgroundColor":"","charSpacing":0,"path":null,"direction":"ltr","minWidth":20,"splitByGrapheme":false,"styles":{}},{"type":"line","version":"4.5.0","originX":"left","originY":"top","left":326.35,"top":32.99,"width":299.4,"height":356.92,"fill":"red","stroke":"red","strokeWidth":5,"strokeDashArray":null,"strokeLineCap":"butt","strokeDashOffset":0,"strokeLineJoin":"miter","strokeUniform":false,"strokeMiterLimit":4,"scaleX":1,"scaleY":1,"angle":0,"flipX":false,"flipY":false,"opacity":1,"shadow":null,"visible":true,"backgroundColor":"","fillRule":"nonzero","paintFirst":"fill","globalCompositeOperation":"source-over","skewX":0,"skewY":0,"x1":-149.70059880239518,"x2":149.70059880239518,"y1":-178.46034214618976,"y2":178.46034214618976},{"type":"line","version":"4.5.0","originX":"left","originY":"top","left":295.41,"top":113.97,"width":256.49,"height":182.96,"fill":"red","stroke":"red","strokeWidth":5,"strokeDashArray":null,"strokeLineCap":"butt","strokeDashOffset":0,"strokeLineJoin":"miter","strokeUniform":false,"strokeMiterLimit":4,"scaleX":1,"scaleY":1,"angle":0,"flipX":false,"flipY":false,"opacity":1,"shadow":null,"visible":true,"backgroundColor":"","fillRule":"nonzero","paintFirst":"fill","globalCompositeOperation":"source-over","skewX":0,"skewY":0,"x1":-128.2435129740519,"x2":128.2435129740519,"y1":91.47967118418131,"y2":-91.47967118418131},{"type":"line","version":"4.5.0","originX":"left","originY":"top","left":215.57,"top":305.93,"width":100.8,"height":170.96,"fill":"red","stroke":"red","strokeWidth":5,"strokeDashArray":null,"strokeLineCap":"butt","strokeDashOffset":0,"strokeLineJoin":"miter","strokeUniform":false,"strokeMiterLimit":4,"scaleX":1,"scaleY":1,"angle":0,"flipX":false,"flipY":false,"opacity":1,"shadow":null,"visible":true,"backgroundColor":"","fillRule":"nonzero","paintFirst":"fill","globalCompositeOperation":"source-over","skewX":0,"skewY":0,"x1":-50.39920159680639,"x2":50.39920159680639,"y1":-85.48100422128417,"y2":85.48100422128417}]}